{"type":"FeatureCollection","features":[{"type":"Feature","geometry":{"type":"Point","coordinates":[28.79081,-2.49682]},"properties":{"name":"FDS","type":"Geopolitique","description":"Date: 06/04/2026\nPays: RDC -  Kabare\nEvenement: Position\nDetail: Le 06/04, des habitants de Kabare (0,9KM/O de Bukavu) ont constaté le retrait présumé des troupes des RDF qui assiégeaient la maison royale depuis plusieurs mois. Des scènes de célébration ont été observées dans les rues. NB : Les populations ont dénoncé des exactions et abus commis par la coalition rebelle durant la période d'occupation.","sources":"Algor_Int_HUMINT|https://algoracces.fr"}},{"type":"Feature","geometry":{"type":"Point","coordinates":[28.746694,-2.330667]},"properties":{"name":"GAE","type":"Geopolitique","description":"Date: 10/04/2026\nPays: RDC - Kalehe\nEvenement: Combat\nDetail: Le 10/04, les miliciens Wazalendo ont repris le contrôle de plusieurs positions dans le territoire de Kalehe, à l'issue de combats intenses contre les rebelles de l'AFC/M23. Les localités de Tushunguti, Matutira et Kimole, dans les villages de Kisha et Mutale, ainsi que Bulembwe sur l'axe Butacha, sont passées sous contrôle des forces loyalistes avant la mi-journée. Pas de bilan disponible.","sources":"Algor_Int_HUMINT|https://algoracces.fr"}},{"type":"Feature","geometry":{"type":"Point","coordinates":[29.01609,-1.62251]},"properties":{"name":"HANI","type":"Attaque","description":"Date: 10/04/2026\nPays: RDC - Shasha\nEvenement: Attaque\nDetail: Dans la nuit du 10 au 11/04, des hommes armés non identifiés ont attaqué le village de Shasha (5KM/SO de Sake), semant la terreur pendant plus d'une heure. Bilan provisoire : 01 civil tué ; 02 blessés évacués vers une structure sanitaire, dont un grièvement blessé à la tête à l'arme blanche et une femme, Furaha Ndembo, touchée par balle au thorax. NB : Le village de Shasha est sous contrôle de la coalition AFC/M23-RDF.","sources":"Algor_Int_HUMINT|https://algoracces.fr"}}]}